LICENSE
README.md
setup.py
hiddenmarkov/__init__.py
hiddenmarkov/utils.py
python_hiddenmarkov.egg-info/PKG-INFO
python_hiddenmarkov.egg-info/SOURCES.txt
python_hiddenmarkov.egg-info/dependency_links.txt
python_hiddenmarkov.egg-info/requires.txt
python_hiddenmarkov.egg-info/top_level.txt