Metadata-Version: 2.1
Name: python-hiddenmarkov
Version: 0.1.3
Summary: A simple Python package for Hidden Markov Models
Home-page: https://github.com/neosatrapahereje/hiddenmarkov
Author: Carlos Cancino-Chacón, Silvan Peter
Author-email: carloscancinochacon@gmail.com
License: MIT
Keywords: hmm hidden_Markov_models
Classifier: License :: OSI Approved :: MIT License
Classifier: Programming Language :: Python
Classifier: Programming Language :: Python :: 3
Classifier: Programming Language :: Python :: Implementation :: CPython
Classifier: Programming Language :: Python :: Implementation :: PyPy
Requires-Python: >=3.6
License-File: LICENSE
